bookCoverSearch.py
setup.cfg
setup.py
bookCoverSearch.egg-info/PKG-INFO
bookCoverSearch.egg-info/SOURCES.txt
bookCoverSearch.egg-info/dependency_links.txt
bookCoverSearch.egg-info/requires.txt
bookCoverSearch.egg-info/top_level.txt